diffhtml/__init__.py
diffhtml/ndiff.py
diffhtml-0.1.1.dist-info/DESCRIPTION.rst
diffhtml-0.1.1.dist-info/METADATA
diffhtml-0.1.1.dist-info/RECORD
diffhtml-0.1.1.dist-info/WHEEL
diffhtml-0.1.1.dist-info/metadata.json
diffhtml-0.1.1.dist-info/top_level.txt
