Metadata-Version: 2.0
Name: diffhtml
Version: 0.1.1
Summary: Tools for generating HTML diff output.
Home-page: https://github.com/uranusjr/diffhtml
Author: Tzu-ping Chung
Author-email: uranusjr@gmail.com
License: ISC license
Keywords: diffhtml
Platform: UNKNOWN
Classifier: Development Status :: 2 - Pre-Alpha
Classifier: Intended Audience :: Developers
Classifier: License :: OSI Approved :: ISC License (ISCL)
Classifier: Natural Language :: English
Classifier: Programming Language :: Python :: 3
Classifier: Programming Language :: Python :: 3.3
Classifier: Programming Language :: Python :: 3.4
Classifier: Programming Language :: Python :: 3.5
Classifier: Programming Language :: Python :: 3.6
Requires-Dist: markupsafe
